intelligent_text2sql/__init__.py
intelligent_text2sql/core/__init__.py
intelligent_text2sql/core/engine.py
intelligent_text2sql/utils/__init__.py
intelligent_text2sql/utils/ambiguity.py
intelligent_text2sql/utils/confidence.py
intelligent_text2sql/utils/db_utils.py
intelligent_text2sql/utils/embedding_utils.py
intelligent_text2sql/utils/fastpath.py
intelligent_text2sql/utils/ollama_client.py
intelligent_text2sql/utils/prompt_builder.py
intelligent_text2sql/utils/schema_formatter.py
intelligent_text2sql/utils/sql_analyzer.py
intelligent_text2sql/utils/sql_cleaner.py
intelligent_text2sql/utils/sql_column_validator.py
intelligent_text2sql/utils/sql_disambiguator.py
intelligent_text2sql/utils/sql_executor.py
intelligent_text2sql/utils/sql_explainer.py
intelligent_text2sql/utils/sql_fixer.py
intelligent_text2sql/utils/sql_table_validator.py
intelligent_text2sql/utils/sql_validator.py
intelligent_text2sql-0.1.1.dist-info/METADATA
intelligent_text2sql-0.1.1.dist-info/WHEEL
intelligent_text2sql-0.1.1.dist-info/top_level.txt
intelligent_text2sql-0.1.1.dist-info/RECORD
