Metadata-Version: 2.4
Name: intelligent-text2sql
Version: 0.1.1
Summary: Offline, schema-aware Text-to-SQL engine with optional LLM backends
Author: Vatsal Patel
License-Expression: MIT
Keywords: text-to-sql,nlp,sql,llm,data-science
Classifier: Programming Language :: Python :: 3
Classifier: Operating System :: OS Independent
Requires-Python: >=3.9
Requires-Dist: pandas
Requires-Dist: sentence-transformers
Requires-Dist: scikit-learn
